README.md
setup.py
pulumiverse_redpanda/__init__.py
pulumiverse_redpanda/_inputs.py
pulumiverse_redpanda/_utilities.py
pulumiverse_redpanda/acl.py
pulumiverse_redpanda/cluster.py
pulumiverse_redpanda/get_cluster.py
pulumiverse_redpanda/get_namespace.py
pulumiverse_redpanda/get_network.py
pulumiverse_redpanda/get_region.py
pulumiverse_redpanda/get_regions.py
pulumiverse_redpanda/get_resource_group.py
pulumiverse_redpanda/get_serverless_cluster.py
pulumiverse_redpanda/get_serverless_regions.py
pulumiverse_redpanda/get_throughput_tiers.py
pulumiverse_redpanda/namespace.py
pulumiverse_redpanda/network.py
pulumiverse_redpanda/outputs.py
pulumiverse_redpanda/provider.py
pulumiverse_redpanda/pulumi-plugin.json
pulumiverse_redpanda/py.typed
pulumiverse_redpanda/resource_group.py
pulumiverse_redpanda/serverless_cluster.py
pulumiverse_redpanda/topic.py
pulumiverse_redpanda/user.py
pulumiverse_redpanda.egg-info/PKG-INFO
pulumiverse_redpanda.egg-info/SOURCES.txt
pulumiverse_redpanda.egg-info/dependency_links.txt
pulumiverse_redpanda.egg-info/not-zip-safe
pulumiverse_redpanda.egg-info/requires.txt
pulumiverse_redpanda.egg-info/top_level.txt
pulumiverse_redpanda/config/__init__.py
pulumiverse_redpanda/config/vars.py