Metadata-Version: 2.1
Name: pulumiverse-redpanda
Version: 0.1.0
Summary: A Pulumi package for creating and managing Redpanda cloud resources.
Home-page: https://www.pulumi.com
License: Apache-2.0
Project-URL: Repository, https://github.com/pulumiverse/pulumi-redpanda
Keywords: pulumi redpanda category/utility
Requires-Python: >=3.9
